openbci_stream/__init__.py
openbci_stream/_version.txt
openbci_stream/acquisition/__init__.py
openbci_stream/acquisition/binary_stream.py
openbci_stream/acquisition/consumer.py
openbci_stream/acquisition/cyton.py
openbci_stream/acquisition/cyton_base.py
openbci_stream/acquisition/tcp_server.py
openbci_stream/daemons/__init__.py
openbci_stream/daemons/stream_bin2eeg.py
openbci_stream/daemons/stream_eeg.py
openbci_stream/daemons/stream_fake_binary.py
openbci_stream/daemons/stream_rpyc.py
openbci_stream/utils/__init__.py
openbci_stream/utils/filters.py
openbci_stream/utils/hdf5.py
openbci_stream/utils/openbci_cli.py
openbci_stream/utils/pid_admin.py
openbci_stream/utils/scan_wifi_modules.py
openbci_stream/utils/viz.py
openbci_stream-1.1.0.data/scripts/openbci_cli
openbci_stream-1.1.0.data/scripts/stream_access_point.sh
openbci_stream-1.1.0.data/scripts/stream_bin2eeg
openbci_stream-1.1.0.data/scripts/stream_configure_kafka.sh
openbci_stream-1.1.0.data/scripts/stream_configure_ntpd.sh
openbci_stream-1.1.0.data/scripts/stream_eeg
openbci_stream-1.1.0.data/scripts/stream_fake_binary
openbci_stream-1.1.0.data/scripts/stream_install_kafka.sh
openbci_stream-1.1.0.data/scripts/stream_rpyc
openbci_stream-1.1.0.data/scripts/stream_tlwr.sh
openbci_stream-1.1.0.dist-info/LICENSE
openbci_stream-1.1.0.dist-info/METADATA
openbci_stream-1.1.0.dist-info/WHEEL
openbci_stream-1.1.0.dist-info/top_level.txt
openbci_stream-1.1.0.dist-info/RECORD
