Metadata-Version: 2.1
Name: openbci-stream
Version: 1.1.0
Summary: High level Python module for EEG/EMG/ECG acquisition and distributed streaming for OpenBCI Cyton board.
Download-URL: https://github.com/UN-GCPDS/openbci_stream
Author: Yeison Cardona
Author-email: yencardonaal@unal.edu.co
Maintainer: Yeison Cardona
Maintainer-email: yencardonaal@unal.edu.co
License: BSD-2-Clause
Classifier: Development Status :: 4 - Beta
Classifier: Intended Audience :: Developers
Classifier: Intended Audience :: Education
Classifier: Intended Audience :: Healthcare Industry
Classifier: Intended Audience :: Science/Research
Classifier: License :: OSI Approved :: BSD License
Classifier: Programming Language :: Python :: 3.8
Classifier: Topic :: Scientific/Engineering
Classifier: Topic :: Scientific/Engineering :: Human Machine Interfaces
Classifier: Topic :: Scientific/Engineering :: Medical Science Apps.
Classifier: Topic :: Software Development :: Embedded Systems
Classifier: Topic :: Software Development :: Libraries
Classifier: Topic :: Software Development :: Libraries :: Application Frameworks
Classifier: Topic :: Software Development :: Libraries :: Python Modules
Classifier: Topic :: System :: Hardware :: Hardware Drivers
Requires-Python: >=3.7
License-File: LICENSE
Requires-Dist: ntplib
Requires-Dist: tables
Requires-Dist: numpy
Requires-Dist: mne
Requires-Dist: requests
Requires-Dist: colorama
Requires-Dist: scipy
Requires-Dist: kafka-python
Requires-Dist: rpyc
Requires-Dist: netifaces
Requires-Dist: python3-nmap
Requires-Dist: pyserial
Requires-Dist: systemd-service
